tests/__init__.py
tests/test_upbeatbot.py
upbeatbot/__init__.py
upbeatbot/main.py
upbeatbot/settings.py
upbeatbot/libs/__init__.py
upbeatbot/libs/api_mock.py
upbeatbot/libs/upbeatbot.py
upbeatbot-0.0.3.dist-info/LICENSE
upbeatbot-0.0.3.dist-info/METADATA
upbeatbot-0.0.3.dist-info/WHEEL
upbeatbot-0.0.3.dist-info/top_level.txt
upbeatbot-0.0.3.dist-info/RECORD
