Metadata-Version: 2.1
Name: upbeatbot
Version: 0.0.3
Summary: Twitter bot to tweet uplifting images at twitter users
Home-page: https://github.com/nickdibari/UpBeatBot
Author: Nicholas DIbari
Author-email: ndibari@fordham.edu
License: UNKNOWN
Platform: UNKNOWN
Classifier: Programming Language :: Python :: 3
Classifier: License :: OSI Approved :: MIT License
Classifier: Operating System :: OS Independent
Requires-Python: >=3.6
Requires-Dist: beautifulsoup4 (==4.4.0)
Requires-Dist: envparse (==0.2.0)
Requires-Dist: python-twitter (==3.5)
